[
    {
        "name": "Los Angeles",
        "height": { "mathjs": "Unit", "value": 1018, "unit": "feet" }
    },
    {
        "name": "New York City",
        "height": { "mathjs": "Unit", "value": 1454, "unit": "feet" }
    },
    {
        "name": "Washington",
        "height": { "mathjs": "Unit", "value": 555, "unit": "feet" }
    },
    {
        "name": "Chicago",
        "height": { "mathjs": "Unit", "value": 1451, "unit": "feet" }
    },
    {
        "name": "Phoenix",
        "height": { "mathjs": "Unit", "value": 483, "unit": "feet" }
    },
    {
        "name": "San Diego",
        "height": { "mathjs": "Unit", "value": 500, "unit": "feet" }
    },
    {
        "name": "Houston",
        "height": { "mathjs": "Unit", "value": 1002, "unit": "feet" }
    },
    {
        "name": "San Francisco",
        "height": { "mathjs": "Unit", "value": 1070, "unit": "feet" }
    },
    {
        "name": "Atlanta",
        "height": { "mathjs": "Unit", "value": 1023, "unit": "feet" }
    },
    {
        "name": "Dallas",
        "height": { "mathjs": "Unit", "value": 915, "unit": "feet" }
    },
    {
        "name": "Boston",
        "height": { "mathjs": "Unit", "value": 790, "unit": "feet" }
    },
    {
        "name": "Seattle",
        "height": { "mathjs": "Unit", "value": 605, "unit": "feet" }
    },
    {
        "name": "San Antonio",
        "height": { "mathjs": "Unit", "value": 750, "unit": "feet" }
    },
    {
        "name": "St Louis",
        "height": { "mathjs": "Unit", "value": 630, "unit": "feet" }
    },
    {
        "name": "Kansas City",
        "height": { "mathjs": "Unit", "value": 624, "unit": "feet" }
    },
    {
        "name": "Philadelphia",
        "height": { "mathjs": "Unit", "value": 973, "unit": "feet" }
    },
    {
        "name": "Jacksonville",
        "height": { "mathjs": "Unit", "value": 620, "unit": "feet" }
    },
    {
        "name": "Detroit",
        "height": { "mathjs": "Unit", "value": 727, "unit": "feet" }
    },
    {
        "name": "Indianapolis",
        "height": { "mathjs": "Unit", "value": 830, "unit": "feet" }
    },
    {
        "name": "Columbus",
        "height": { "mathjs": "Unit", "value": 629, "unit": "feet" }
    },
    {
        "name": "Toronto",
        "height": { "mathjs": "Unit", "value": 1814, "unit": "feet" }
    },
    {
        "name": "Montreal",
        "height": { "mathjs": "Unit", "value": 743, "unit": "feet" }
    },
    {
        "name": "Vancouver",
        "height": { "mathjs": "Unit", "value": 659, "unit": "feet" }
    },
    {
        "name": "Ottawa",
        "height": { "mathjs": "Unit", "value": 367, "unit": "feet" }
    },
    {
        "name": "Mississauga",
        "height": { "mathjs": "Unit", "value": 518, "unit": "feet" }
    },
    {
        "name": "Edmonton",
        "height": { "mathjs": "Unit", "value": 646, "unit": "feet" }
    },
    {
        "name": "Winnipeg",
        "height": { "mathjs": "Unit", "value": 420, "unit": "feet" }
    },
    {
        "name": "Calgary",
        "height": { "mathjs": "Unit", "value": 626, "unit": "feet" }
    },
    {
        "name": "Mexico City",
        "height": { "mathjs": "Unit", "value": 807, "unit": "feet" }
    },
    {
        "name": "Guadalajara",
        "height": { "mathjs": "Unit", "value": 705, "unit": "feet" }
    },
    {
        "name": "Puebla",
        "height": { "mathjs": "Unit", "value": 650, "unit": "feet" }
    },
    {
        "name": "Tijuana",
        "height": { "mathjs": "Unit", "value": 334, "unit": "feet" }
    }
]
